{
    "director": [
        "Tim Hill"
    ],
    "writer": [
        "Jon Vitti",
        "Will McRobb",
        "Chris Viscardi"
    ],
    "producer": [
        "Ross Bagdasarian Jr.",
        "Michele Imperato",
        "Janice Karman",
        "Christopher Meledandri",
        "Arnon Milchan",
        "Michele Panelli-Venetis",
        "Karen Rosenfelt",
        "Steve Waterman"
    ],
    "composer": [
        "Christopher Lennertz"
    ],
    "cinematographer": [
        "Peter Lyons Collister"
    ],
    "editor": [
        "Peter E. Berger"
    ],
    "art direction": [
        "Charlie Daboub"
    ],
    "set decoration": [
        "Anne D. McCulley"
    ],
    "make up": [
        "Elena Arroy",
        "Kim Beaird",
        "Ora Green",
        "Yuko T. Koach",
        "Maynard Matthews",
        "Cheri Minns",
        "Peggy Teague",
        "Toni-Ann Walker",
        "Jose Zamora"
    ],
    "production manager": [
        "Debra K. Chinn",
        "Michele Imperato",
        "David McKimmie",
        "Leigh Shanta"
    ],
    "assistant director": [
        "Thomas E. Ackerman",
        "Christian Clarke",
        "Michael W. Crotty",
        "Rusty Mahmood",
        "David Mendoza",
        "Michele Panelli-Venetis",
        "Timothy R. Price",
        "Kea Zemans"
    ],
    "art department": [
        "Sharon E. Alshams",
        "Fred Apolito",
        "George Atamian",
        "Ronald S. Baratie",
        "Jiye Choi",
        "Matthew D. Egan",
        "Melissa Elbaum",
        "Alyssa Feener",
        "Emily Ferry",
        "Ilana Gordon",
        "George E. Hanson",
        "Charli Jayson",
        "Tommy John",
        "Eric Kelly",
        "Robert E. Knight",
        "Buck Lewis",
        "Angelo Libutti",
        "Frank McEldowney",
        "Robert Misetich",
        "Wayne Nycz",
        "Tony Paolone",
        "Edmond Scott Ratliff",
        "Steve Rice",
        "Rosendo L. Rivas III",
        "Stephen Runningen",
        "Lissette Schettini",
        "Craig T. Shordon",
        "Jesse Siono Jr.",
        "Bob Skemp",
        "David Stephan",
        "John L. Sullivan",
        "Joy Taylor",
        "Steven C. Voll",
        "Greg Wilkinson",
        "Emily A. Wilson",
        "Craig Zumbroegel",
        "James Beihold",
        "Joe Haidar",
        "Hannah M. Hinkel",
        "Lars Petersen"
    ],
    "sound crew": [
        "Panos Asimenios",
        "Michael Axinn",
        "Derek Casari",
        "Scott Curtis",
        "Gloria D'Alessandro",
        "Susan Dawes",
        "Mark DeSimone",
        "Dawn Fintor",
        "Christopher Flick",
        "David Giammarco",
        "Tim Gomillion",
        "Galen Goodpaster",
        "Jeffory Haddad",
        "Paulino Hemmer",
        "Larry Hopkins",
        "Mildred Iatrou",
        "Doug Jackson",
        "R.J. Kizer",
        "Tony Lamberti",
        "David Lucarelli",
        "David Macmillan",
        "Paul Massey",
        "Tim Maxwell",
        "Jordan O'Neill",
        "Jan Petrov",
        "Erin Michael Rettig",
        "Charleen Richards",
        "Dennis Rogers",
        "Abel Schiro",
        "Christine Sirois",
        "William Stein",
        "Alicia Stevenson",
        "Jon Vogl",
        "John Soukup"
    ],
    "special effects": [
        "Douglas Calli",
        "Alan E. Lorimer",
        "William H. Schirmer"
    ],
    "visual effects": [
        "Alberto Abril",
        "Jude Adamson",
        "Jesse Alexander",
        "Samuel Alicea",
        "Jeff Allen",
        "James Andrykowski",
        "Ashima Taneja Arora",
        "Ronald Arredondo",
        "Nicholas Augello",
        "Randall Bahnsen",
        "David Bailey",
        "Bhavika Bajpai",
        "Anand Balasubramaniam",
        "Adam Balentine",
        "Lyndon Barrois",
        "Casey James Basichis",
        "Brooke Beane",
        "Mike Beaulieu",
        "Jeffery Beeland",
        "Bryan Bentley",
        "Chris Bergman",
        "Beverly Bernacki",
        "Anita Bevelheimer",
        "Abhishek Bharadwaj",
        "Emil Bidiuc",
        "Rohit Bindal",
        "John Blalock",
        "Adam Blank",
        "Kirstin Blythe",
        "Sathish Kumar Bodicherla",
        "Swapnil Borawake",
        "Jennifer Bourne",
        "Edward Derian Boyke",
        "Ellen Brenner",
        "David Brickley",
        "Matt Brown",
        "Sebastien Bruneau",
        "Brian Brunst",
        "Josh Bryer",
        "Alexandra Bryman",
        "Christopher Burel",
        "Nicholas Burkard",
        "Paul Bush",
        "Rommel S. Calderon",
        "Justin Callanan",
        "Francis L. Camacho",
        "Donna Camargo",
        "Brian Campbell",
        "Georgia Cano",
        "Keanan Cantrell",
        "Tom Capizzi",
        "Jeffrey Castel De Oro",
        "Tyler Cayce",
        "Jessica Chan",
        "Kent Chan",
        "Kee Chang",
        "Serena Chang",
        "Jo-Wan Chao",
        "Tamar Chatterjee",
        "Yeen-Shi Chen",
        "Arun P. Chidambaram",
        "Raymond Chih",
        "Kunal Chindarkar",
        "Jiyeon Cho",
        "Jung-Yoon Choi",
        "Jeffrey Cilley",
        "David Cole",
        "Chris Consani",
        "Kevin Coutinho",
        "Donnie Creighton",
        "Elizabeth Cross",
        "Ana Marie Cruz",
        "Tim T. Cunningham",
        "Amanda Dague",
        "Umesh Dalvi",
        "Rajdeep Dandekar",
        "Payal Dani",
        "Jubin Dave",
        "Nirmal David",
        "Jose L. De Juan",
        "Eric Dehaven",
        "Sandy DellaMarie",
        "Mike Demur",
        "Radha Desai",
        "Venuprasath Dhanapal",
        "Jenny Dias",
        "Jessica Dixon",
        "John Dowell",
        "Steve Dubin",
        "Ryan Duhaime",
        "Pauline Duvall",
        "Carolyn Ee-Kaiser",
        "John Egli",
        "Colin Elliott",
        "Jesse Ellis",
        "Chris Elmer",
        "Richard Enders",
        "Ryan English",
        "Jenn Epstein",
        "Rich Fallat",
        "Alexander Fernandes",
        "Dan Foster",
        "Tyler Fox",
        "Adam Francis",
        "Jay Frankenberger",
        "Wes Franklin",
        "Patricia Frazier",
        "Nina Fricker",
        "Matthew Fuller",
        "Sarah Fuller",
        "Sagar Funde",
        "Nicole Galaz",
        "Ginesh Gandhi",
        "Victor J. Garza",
        "Pranav Kumar Gautam",
        "Divakar Ghodake",
        "Daniel Gilbert",
        "Logan Gloor",
        "Keith Goldfarb",
        "Paula Goldstein",
        "Maria Gonzales",
        "Daniel Gonzalez",
        "John Goodman",
        "Jimmy Gordon",
        "Joanna N. Goslicka",
        "Victor Grant",
        "Aaron Grey",
        "Eddie Guiterez",
        "Anisha Gupta",
        "Michael Guttman",
        "Jennifer Hager",
        "Justin Hammond",
        "Dan Haring",
        "Walid Harmoush",
        "Anthony Harris",
        "Ellen Harris",
        "Ryan Helsley",
        "Joshua Herrig",
        "Shweta Hirani",
        "Chrysta Hiser",
        "Pablo Holcer",
        "Phil Holland",
        "Markus Houy",
        "Lee Hoya",
        "Jared Hromika",
        "Gerry Hsu",
        "Pearl Hsu",
        "Melissa Huerta",
        "Jamie Huey",
        "Kenton Hulme",
        "Dartayous Hunter",
        "Sean Hyunin Lee",
        "Neeraj Ingle",
        "Katherine Ipjian",
        "Vinita Iyer",
        "Andreas Jablonka",
        "Kevin Jackson",
        "Virendra Jadhav",
        "Babul Jain",
        "Sarahjane Javelo",
        "Christopher Johnson",
        "Cathy Jones",
        "Marvin Jones",
        "Heather Jones-Pryor",
        "Jongo",
        "Mack Kablan",
        "Sean Kaczmarek",
        "Michael Kambli",
        "Snehal Kanchan",
        "Prabhav Katdare",
        "Sean Kennedy",
        "Chris J. Kenny",
        "Hannah Kent",
        "Scott Kilburn",
        "Chansoo Kim",
        "Sam Kim",
        "Si-Hyung Kim",
        "Vemulapalli Sasi Kiran",
        "Shelagh Kitney",
        "Karen Klein",
        "Lisa Klein",
        "Bomsok Ku",
        "Aaron Kupferman",
        "Prince Kurian",
        "Kenneth Kurras",
        "Yogesh Lakhani",
        "Harry Lam",
        "Jaymie Lam",
        "Kai-Hua Lan",
        "Vincent Lavares",
        "Dan Lazarow",
        "Alfredo Leandro",
        "Alexander K. Lee",
        "Young Lee",
        "Matthew Leishman",
        "Frederick LeMaster",
        "Stephen Les",
        "Rebecca Lilienfeld",
        "Daniel Lindsey",
        "Mark Lipsmeyer",
        "Lu Liu",
        "Russell Lloyd II",
        "Sophia Lo",
        "Trevor Lorber",
        "Erica Loza",
        "Daniel Macarin",
        "Mary Lynn Machado",
        "Matt Magnolia",
        "Varun Malhotra",
        "Jason Malinowsky",
        "Karey Maltzahn",
        "Vangala Manoj",
        "Simon Marinof",
        "Michael T. Marlett",
        "Shawn Mason",
        "Gaurav Mathur",
        "Noel McGinn",
        "Chris McLeod",
        "M. Gavin McMillan",
        "Gagan Mehta",
        "Jay Mehta",
        "Daniel Mejia",
        "Amit Meshram",
        "Christopher Michael",
        "Christopher Mills",
        "Jennifer Mizener",
        "Ken Mohamed",
        "Sheila Molnar",
        "Rohini Montenegro",
        "Jim Moorhead",
        "Zeke Morales",
        "Meg Morris",
        "Adam Moura",
        "Anandroop Mukherjee",
        "Shane Mulholland",
        "Ram Mohan Nadam Reddy",
        "Michael Nair",
        "Samuel Nair",
        "Rishikesh Nandlaskar",
        "Anita Naufal",
        "Brandon Nelson",
        "Alana Newell",
        "Thai-My Nguyen",
        "Samuel Nunez",
        "Chibueze Ogamba",
        "Carina Ohlund",
        "Tyler Opatrny",
        "Warren Paeff",
        "Kaushik Pal",
        "Tejal Pandkar",
        "Ken Paris",
        "Charles Parrish",
        "Zach Parrish",
        "Nikki Pataracchia",
        "Brett Paton",
        "Vishal Pawar",
        "Angelica Perez",
        "Rebecca Perez",
        "David Perkins",
        "Jean Joseph Philip",
        "Vaibhav Piwlatkar",
        "Tim Pixton",
        "Alex Poei",
        "Joshi Prajakta",
        "Kevin Rafferty",
        "Andres Rascon",
        "Marina Ratina",
        "Kedar Raut",
        "Aatur Ravani",
        "Suryapal Rawat",
        "David Rhodes",
        "Burke Roane",
        "Trey Roane",
        "Mikki Rose",
        "Matthew Rubin",
        "Rebecca Ruether",
        "Karl Rumpf",
        "Saswat Sahoo",
        "Joe Salazar",
        "Mayuresh Salunke",
        "Neha Samant",
        "Arnab Sanyal",
        "Chingkhei Sapam",
        "CJ Sarachene",
        "Jeffrey Schaper",
        "Tiffany Schmitter",
        "Chad Sellers",
        "Divyesh Shah",
        "Siddharth Shah",
        "Chad Shattuck",
        "Shreya Shetty",
        "Jackie Shibles",
        "Todd Shifflett",
        "Nidhi Shrivastava",
        "Josh Shuman",
        "Peter Sidoriak",
        "Cybele Sierra",
        "Sabrina Silver",
        "Andrew Silvestri",
        "Lulu J. Simon",
        "Dhruv Singh",
        "Ryan Sivley",
        "Amie Slate",
        "Jason Smith",
        "Jakris Smittant",
        "Carlos Solorzano",
        "Danny Speck",
        "Christopher Stanczak",
        "Jason Stansell",
        "Timothy Steele",
        "Jon Stein",
        "Jennifer Stratton",
        "Yuki Sugimoto",
        "Radhakrishnan Sundararaj",
        "Kenny Sutherland",
        "Ryan Swanno",
        "Brian Tatosky",
        "Will Telford",
        "Kevin Tengan",
        "Jateen Thakkar",
        "Cat Thelia",
        "Lindsay Thompson",
        "Marc Thyng",
        "Josh Tomlinson",
        "Ferdinand Torres",
        "Tejas Trivedi",
        "Vincent Truitner",
        "Arati Ullal",
        "Sourabh Uppal",
        "Richard Van Cleave Jr.",
        "Dileep Varma",
        "John Vassallo",
        "Sharmila Venugopal",
        "Scott Vosbury",
        "Erika Wangberg Burton",
        "Diana Marie Wells",
        "D'Lun Wong",
        "Pam Wong",
        "Christian Wood",
        "Rinkesh Yadav",
        "Adam Yaniv",
        "Gee Yeung",
        "Kent Yoshida",
        "Brandy Zumkley",
        "Amit Aidasani",
        "Shish Aikat",
        "Erik Akutagawa",
        "Mandy Arnold",
        "Saraswathi Balgam",
        "Lee Berger",
        "Nikhil Bhatnagar",
        "Hitesh Chikate",
        "Vikas Chirate",
        "Sandesh Chonkar",
        "Daniel Aristoteles Collins",
        "Chris De St Jeor",
        "Paresh Dedhia",
        "Yoshi DeHerrera",
        "Ashutosh Deshmukh",
        "Amol Dighe",
        "Philip Duncan",
        "Sean Keith Fernandes",
        "Chris Flynn",
        "Anthony Fung",
        "Christina Garberson",
        "Varun Hadkar",
        "Harrison Hays",
        "John Hughes",
        "Lakshmi Subramanian Iyer",
        "Kamalakkannan",
        "John Kilkenny",
        "Yun Jung Kim",
        "Sijo Kolenchery",
        "Danny Lei",
        "David Linsey",
        "Richard Mahon",
        "Liam Major",
        "Joe Mancewicz",
        "Bruce Mann",
        "L. Patrick McCormack",
        "Jane M. McCurley",
        "Douglas Miller",
        "Rohini Montenegro",
        "Vanessa Mylchreest",
        "Prajakta Nandlaskar",
        "Christopher S. Nielsen",
        "Jim O'Hagan",
        "Nathan Ortiz",
        "Jessica Papstein",
        "Sanjit Patel",
        "Seth Peterson",
        "Perry Petrzilka",
        "Poonam Maria Prem",
        "Nick Pugh",
        "Vivek Ram",
        "Shrinidhi Rao",
        "Diksha Sagar",
        "Yogesh Sawant",
        "Seshaprasad",
        "Shyamchand",
        "Murugan Siju",
        "Arjun Singh",
        "Mandeep Singh",
        "Brad Smith",
        "Jeff W. Smith",
        "Hitesh Solanki",
        "Viral Vadalia",
        "Rakesh Venugopalan",
        "Nate Yellig",
        "Robert Young",
        "Sagar Zade"
    ],
    "stunt performer": [
        "Jennifer Cobb",
        "Norman Epperson",
        "Debbie Evans",
        "George Fisher",
        "Matt Leonard",
        "Svetlana Markel",
        "Buck McDancer",
        "Rick Miller",
        "John Moio",
        "John Robotham",
        "Jim Stephan",
        "Jeffrey C. Robinson"
    ],
    "camera and electrical department": [
        "Thomas E. Ackerman",
        "Gerald Autin",
        "Noah Behar",
        "Ryan Bradley",
        "Matthew Brookman",
        "Alan Brownstein",
        "Robin Bursey",
        "Devin Campbell",
        "Greg Cantrell",
        "Steve Charnow",
        "Alan Colbert",
        "Craig Cooper",
        "Richard Crow",
        "Jesse Crusing",
        "Christopher Cundey",
        "Gary Dahlquist",
        "Charlie Dalrymple",
        "Josh Day",
        "Darrin DeLoach",
        "Alan R. Disler",
        "Shawn Ensign",
        "Michael S. Epley",
        "Bryan Fletchall",
        "Michael Franco",
        "Franc Gabusi",
        "Patrick George",
        "Christopher Glasgow",
        "Andrew B. Horton",
        "Shane D. Kelly",
        "Doug Lerma",
        "James A. Lundin",
        "Dominic Mazzola",
        "David J. McGraw",
        "David L. Parrish",
        "Les Percy",
        "Michael C. Price",
        "Robert Reid",
        "Landon Ruddel",
        "Ramiro Ruiz",
        "Brian Scotti",
        "Michael Shanman",
        "Frank R. Sims",
        "Randy Tambling",
        "Andrew Taylor",
        "Tommy Tieche",
        "Jaimie Trueblood",
        "Chris Updegrave",
        "Scott Webb",
        "Dave Wood",
        "Tom Wostak",
        "Jason Young"
    ],
    "costume department": [
        "Jennifer Dozier",
        "Adrienne Greshock",
        "A.J. Hess",
        "Unchin Lee",
        "Viviana Pascual",
        "Emma Trenchard",
        "Deborah Zimmerman"
    ],
    "music department": [
        "Nico Abondolo",
        "Richard Altenbach",
        "Armen Anassian",
        "Brett Banducci",
        "Rick Baptist",
        "Steve Becknell",
        "Chris Bleth",
        "Bill Booth",
        "Tom Boyd",
        "Jacqueline Brand",
        "Rob Brophy",
        "Tom Brown",
        "Darius Campo",
        "Judy Chilnick",
        "Heather Clark",
        "Giovana Clayton",
        "Kevin Connolly",
        "Franklyn d'Antonio",
        "Alana Da Fonseca",
        "Ali Dee",
        "Brian Dembow",
        "Joel Derouin",
        "Marcia Dickstein",
        "George Doering",
        "Andrew Duckles",
        "Bruce Dukov",
        "Timothy Eckert",
        "Robert Elhai",
        "Alan Estes",
        "Nina Evtuhov",
        "Alma L. Fernandez",
        "Don Ferrone",
        "Nick Fevola",
        "Marlo Fisher",
        "Samuel Formicola",
        "Matt Franko",
        "Vanessa Freebairn-Smith",
        "Matthew Funes",
        "Rossano Galante",
        "Julie Gigante",
        "Kevin Globerman",
        "Gregory T. Goodall",
        "M.B. Gordy",
        "Agnes Gottschewski",
        "Mark Graham",
        "Endre Granat",
        "Danny Greco",
        "Keith Greene",
        "Michael E. Grego",
        "Trevor Handy",
        "John Hayhurst",
        "Amy Hershberger",
        "Henry Hey",
        "Oscar Hidalgo",
        "Fred Irby",
        "Sharon Jackson",
        "Maia Jasper",
        "Rebecca Jones",
        "Julianne Jordan",
        "Steve Juliani",
        "Alan Kaplan",
        "Dennis Karmazyn",
        "Roland Kato",
        "Joey Katsaros",
        "Dan Kelley",
        "Peter Kent",
        "Brian Kilgore",
        "Andrew Kinney",
        "Paul Klintworth",
        "Mike Knobloch",
        "Robert Kraft",
        "Aimie Kreston",
        "Armen Ksajikian",
        "Steve Kujala",
        "Timothy Landauer",
        "Michael Lang",
        "Roger Lebow",
        "Songa Lee",
        "Jinny Leem",
        "Christopher Lennertz",
        "Phillip Levy",
        "Dane Little",
        "Michael J. Lloyd",
        "Lora'nd Lokustza",
        "Timothy Loo",
        "David Low",
        "Rene Mandel",
        "Peter Mandell",
        "Shawn Mann",
        "Marina Manukian",
        "Michael Markman",
        "Luke Maurer",
        "John McCurry",
        "Ed Meares",
        "Steven Memel",
        "Victoria Miskolczy",
        "Michael Mollo",
        "Kristy Morrell",
        "Tim Morrison",
        "Kenneth Munday",
        "Helen Nightengale",
        "Dana Niu",
        "Sheila Owens",
        "Joel Pargman",
        "David Parmeter",
        "Nicolas Philippon",
        "Andrew Picken",
        "Movses Pogossian",
        "Katia Popov",
        "Chang Qu",
        "Leslie Reed",
        "Bill Reichenbach",
        "Larry Rench",
        "John Reynolds",
        "Michele Richards",
        "Cassandra Richburg",
        "Carolyn Riley",
        "Rafael Rishik",
        "Susan Rishik",
        "Brandon Roberts",
        "Mark Robertson",
        "Bart Samolis",
        "Marni Sanders",
        "Michael Sandlofer",
        "George Kim Scholes",
        "Jim Self",
        "David Shostac",
        "Andrew Shulman",
        "Steven L. Smith",
        "Tereza Stanislav",
        "Lisa M. Sutton",
        "James Thatcher",
        "Sarah Thornblade",
        "Sebastian Toettcher",
        "Josefina Vergara",
        "James Walker",
        "Matthew J. Ward",
        "Philip White",
        "Roger Wilkie",
        "Mark Jan Wlodarkiewicz",
        "Frances Liu Wu",
        "Ge-Fang Yang",
        "Phillip Yao",
        "Kenneth Yerke",
        "David Young",
        "Thomas Cavanaugh",
        "Ellen Ginsburg"
    ],
    "script department": [
        "Susan Bambara",
        "Rebecca Robertson"
    ],
    "transportation department": [
        "Linda Cipperley",
        "Daniel Davis",
        "J. Armin Garza II",
        "Brian D. Hall",
        "Garner Humphrey",
        "Robert K. Johnson",
        "Alana McGaughy",
        "Tina Peterson",
        "Yvette Peterson",
        "John 'J.P.' Pratt",
        "Brian Stackhouse",
        "Mark Valdez",
        "Ron Windred"
    ],
    "miscellaneous crew": [
        "Wendy Altman-Cohen",
        "Jessica Babila",
        "Vanessa Bagdasarian",
        "Wayne Barker",
        "Bradford Berling",
        "Charlie Bolwell",
        "Jane Bulmer",
        "John Caccese",
        "Brian Carroll",
        "John Cohen",
        "Brad Combs",
        "Cody D'Ambrosio",
        "David Dahn",
        "Scott Everett White",
        "Zack Ewing",
        "Taylor M. Favale",
        "James Ferrera",
        "Colin Galloway",
        "Wendy Geary",
        "Johnny Gidcomb",
        "Jeremy Glazer",
        "Katherine Grace",
        "Stephanie Fitch Groff",
        "Dan Harder",
        "Mike Harrington",
        "Pete Hernandez",
        "Roy G. Irwin",
        "Teresa Jaime Drapkin",
        "Jason Jancosek",
        "Walter Jones",
        "Maria Lebsock",
        "Hope Levy",
        "Sharon Lopez",
        "James E. Maddux",
        "Tammy Masters",
        "Krystal Mathiesen",
        "Rob McCabe",
        "Rosero McCoy",
        "Meredith McIvor",
        "Randy McKenney",
        "Christopher Meledandri",
        "Robin E. Michels",
        "Lisa Lee Morgan",
        "Aditi Nagjee",
        "Sam Nainoa",
        "Max Newman",
        "Steve Pacheco",
        "Devika Parikh",
        "John Parker",
        "Ron Pekkala",
        "Kenneth Pelletier",
        "Juan Gabriel Perez Arjona",
        "Myleshia Perryman",
        "Marisa Rico",
        "Damani Roberts",
        "Jennifer Schrauwers",
        "Justin Shenkarow",
        "Jason Grant Smith",
        "Warren Sroka",
        "Charline St. Charles",
        "Mark Sussman",
        "Vonetta Taylor",
        "Jennifer Visalli",
        "Monica Vulcano",
        "Linda Warrilow",
        "Lash\u00e1 Monique Winn",
        "Kevin Zelman",
        "Patty Connolly",
        "Christina Hwang",
        "David A. Starke"
    ],
    "cast": [
        "Jason Lee",
        "David Cross",
        "Cameron Richardson",
        "Jane Lynch",
        "Justin Long",
        "Matthew Gray Gubler",
        "Jesse McCartney",
        "Allison Karman",
        "Tiara Parker",
        "Kira Verrastro",
        "Veronica Alicino",
        "Beth Riesgraf",
        "Adriane Lenox",
        "Don Tiffany",
        "Lorne Green",
        "Kevin Symons",
        "Frank Maharajh",
        "Greg 'G-Spot' Siebel",
        "Oliver Muirhead",
        "Jayden Lund",
        "Erin Chambers",
        "Jillian Barberie",
        "Chris Classic",
        "Adam Riancho",
        "Axel Alba",
        "Rosero McCoy",
        "Alexis Boyd",
        "Criscilla Anderson",
        "Kevin Fisher",
        "Kyndra Reevey",
        "Tucker Barkley",
        "Celestina",
        "Laura Edwards",
        "Christopher Scott",
        "Miss Prissy",
        "Bryan Gaw",
        "Michelle Maniscalco",
        "Nick Drago",
        "Melanie Lewis",
        "Karen-Marie Ali",
        "Ross Bagdasarian Jr.",
        "Jay Bird",
        "Colette Claire",
        "Natalie Cohen",
        "Sommer Fehmel",
        "Kevin Fung",
        "Karl Jacobs",
        "Heaven Lee Porteous Jent",
        "Janice Karman",
        "Samantha Kelly",
        "Gregg Lee",
        "Lisa Mason Lee",
        "Eddie Mariano",
        "Xian Mikol",
        "Meghan Noone",
        "Chris Rossi",
        "Jameel Saleem",
        "Melanie Stephens",
        "Tony Swift",
        "Steve Vining",
        "Brianna Womick",
        "Maria Zambrana"
    ],
    "name": "Alvin and the Chipmunks"
}