{
    "director": [
        "Joel Zwick"
    ],
    "writer": [
        "Nia Vardalos"
    ],
    "producer": [
        "Paul Brooks",
        "David Coatsworth",
        "Gary Goetzman",
        "Tom Hanks",
        "Mark Hufnail",
        "Jim Milio",
        "Melissa Jo Peltier",
        "Steve Shareshian",
        "Norm Waitt",
        "Rita Wilson"
    ],
    "composer": [
        "Alexander Janko",
        "Chris Wilson"
    ],
    "cinematographer": [
        "Jeffrey Jur"
    ],
    "editor": [
        "Mia Goldman"
    ],
    "art direction": [
        "Kei Ng"
    ],
    "set decoration": [
        "Enrico Campana"
    ],
    "make up": [
        "Ann Brodie",
        "Judi Cooper-Sealy",
        "Paul R.J. Elliot",
        "Burton LeBlanc",
        "Sandra Reynolds",
        "Beatrice Salazar",
        "Dorota Zajac"
    ],
    "production manager": [
        "D.J. Carson",
        "David Coatsworth",
        "Isabel Henderson"
    ],
    "assistant director": [
        "Jennifer C\u00f4t\u00e9",
        "Grant Lucibello",
        "David McAree",
        "Effy Papadopoulos",
        "Odette Blanch",
        "Lorin Raine"
    ],
    "art department": [
        "Brenton Brown",
        "Jacinta Cooper",
        "Imre de Jonge",
        "Katia de Pe\u00f1a",
        "Rossana DeCampo",
        "Alan Doucette",
        "Gary Harmer",
        "Gordon Lebredt",
        "Tim Ovans",
        "Mark Thomson",
        "Alan Tremaine",
        "Martin Weinryb",
        "Wayne Wightman"
    ],
    "sound crew": [
        "Paul Timothy Carden",
        "Brian Dixon",
        "Dean Drabin",
        "Kimberly Harris",
        "Donald Hauger",
        "Thomas Hayek",
        "Paul Holzborn",
        "Tom Mather",
        "Thomas O'Neil Younkman",
        "Geoffrey G. Rubay",
        "Melissa Sherwood Hofmann",
        "Tulio Torrinello",
        "Tami Treadwell",
        "Mark Wolfson",
        "James Wright",
        "Alfonso Calvo",
        "Jeff Glueck",
        "Nancy MacLeod",
        "Melissa Sherwood Hofmann"
    ],
    "special effects": [
        "Martin Malivoire",
        "Peter Sissakis"
    ],
    "visual effects": [
        "Steve Rundell",
        "Brian Allan",
        "Christopher Dusendschon",
        "Steven Emmert",
        "Adam Howard"
    ],
    "stunt performer": [
        "Marco Bianco"
    ],
    "camera and electrical department": [
        "Nick Bacon",
        "Rod Benjamin",
        "Andy Chmura",
        "John Colavecchia",
        "Sean Dawes",
        "Cylvan Desrouleaux",
        "Michael Galbraith",
        "Sophie Giraud",
        "Greg Grainger",
        "R. Jones",
        "Rod MacNeil",
        "Keith Murphy",
        "Tom O'Hara",
        "Michael Plant",
        "Jesse Stanley",
        "Tom Starnes",
        "Robert Vigus",
        "Victor Vukosavljevic",
        "Mark W. Hindle",
        "Mike Nixon",
        "Greg Whiteside",
        "Richard Wilmot"
    ],
    "costume department": [
        "Carole Costello",
        "Jay Du Boisson",
        "Jane Flanders",
        "Gisella Zomparelli",
        "Karen Meluck"
    ],
    "music department": [
        "Nico Abondolo",
        "Deva Anderson",
        "Gary Bovyer",
        "Tom Calderaro",
        "Jon Clarke",
        "Tim Comstock",
        "Franklyn d'Antonio",
        "Bruce Dukov",
        "Steve Erdody",
        "Robert Fernandez",
        "Marlo Fisher",
        "Matthew Funes",
        "Armen Garabedian",
        "Alex Gibson",
        "Thomas Graham II",
        "Endre Granat",
        "Alan Grunfeld",
        "Gregory Jamrok",
        "Alexander Janko",
        "Randy Kerber",
        "Miran Kojian",
        "Aimie Kreston",
        "Armen Ksajikian",
        "Dimitrie Leivici",
        "Phillip Levy",
        "Rebecca R. Liddle",
        "David Low",
        "Darrin McCann",
        "Ed Meares",
        "Victoria Miskolczy",
        "Simon Oswell",
        "Dean Parks",
        "Katia Popov",
        "Jeremy Raub",
        "Rafael Rishik",
        "Delphine Robertson",
        "Mark Robertson",
        "Marc Sazer",
        "Haim Shtrum",
        "Sebastian Toettcher",
        "Cecilia Tsan",
        "Louise Di Tullio",
        "Michael Valerio",
        "Josefina Vergara",
        "David Walther",
        "Chris Wilson",
        "Kenneth Yerke",
        "Tom Boyd",
        "Neil Citron",
        "Robert Fernandez",
        "Mark Wolfson"
    ],
    "script department": [
        "Daniela Saioni",
        "Tami Thomson",
        "Michelle Dunton"
    ],
    "transportation department": [
        "Al Donin",
        "Norman Foster",
        "Ray Gabourie",
        "Bill Hagan",
        "John Hiltz",
        "Savvas Paraskevas",
        "Jeff Peebles",
        "Doug Perry",
        "Don Retzer"
    ],
    "miscellaneous crew": [
        "Brandi Andersen",
        "Mardie Anderson",
        "Trudy Artman",
        "Sebastian Bauer",
        "Lesia Capone",
        "Louise Casey",
        "Christopher G. Cowen",
        "Greg Eby",
        "Pablo Ferro",
        "Nancy Vardalos Ginakes",
        "Katharine Gray",
        "Leah Holmes",
        "David Hutkin",
        "Monica Ionson",
        "Helen Lucas",
        "Amy McKenzie",
        "Lara McMahon",
        "John Nelles",
        "Eric E. Paulson",
        "Kostas Petsis",
        "J.R. Powell",
        "Breigh Radford",
        "JoAnne Rivers",
        "Marsha Robertson",
        "Marissa Roman",
        "Patricia Satok",
        "Tom Tobin",
        "John Von Atzigen",
        "David Zikovitz",
        "Michael Barnes",
        "Gregory Diamond",
        "Joanna L. Rees Jones",
        "Immanuel Spira",
        "Jeanne Van Cott",
        "George Veras"
    ],
    "cast": [
        "Nia Vardalos",
        "Michael Constantine",
        "Christina Eleusiniotis",
        "Kaylee Vieira",
        "Johnny Kalangis",
        "Lainie Kazan",
        "Marita Zouravlioff",
        "Sarah Osman",
        "Petra Wildgoose",
        "Melissa Todd",
        "Bess Meisler",
        "Andrea Martin",
        "Louis Mandylor",
        "Gerry Mendicino",
        "Stavroula Logothettis",
        "Constantine Tsapralis",
        "Gia Carides",
        "Joey Fatone",
        "John Corbett",
        "Ian Gomez",
        "Jayne Eastwood",
        "Frank Falcone",
        "Eugene Martel",
        "Joe Persechini",
        "Peter Xynnis",
        "Fiona Reid",
        "Bruce Gray",
        "Anthony Kandiotis",
        "Nick Kutsukos",
        "Peter Tharos",
        "Chrissy Paraskevopoulos",
        "Maria Vacratsis",
        "Kathryn Haggis",
        "Gale Garnett",
        "Charlene Bitzas",
        "Chris Savides",
        "Constantine Vardalos",
        "Scott Khouri",
        "John Tsifliklis",
        "Peter Chalkiopoulos",
        "Peter Gogos",
        "Spiro Milankou",
        "Victor Politis",
        "Jim Rouvas",
        "Arielle Sugarman",
        "Matthew Galliford",
        "Thomas Kane",
        "Konstantine Kurelias"
    ],
    "name": "My Big Fat Greek Wedding"
}