{
    "director": [
        "Colin Strause",
        "Greg Strause"
    ],
    "writer": [
        "Joshua Cordes",
        "Liam O'Donnell"
    ],
    "producer": [
        "Kristian James Andresen",
        "Paul Barry",
        "Liz Dean",
        "Brian Kavanaugh-Jones",
        "Tracey Landon",
        "Liam O'Donnell",
        "Brett Ratner",
        "Vim Shanmugam",
        "Colin Strause",
        "Greg Strause",
        "Brian Tyler"
    ],
    "composer": [
        "Matthew Margeson"
    ],
    "cinematographer": [
        "Michael Watson"
    ],
    "editor": [
        "Nicholas Wayman-Harris"
    ],
    "art direction": [],
    "set decoration": [],
    "make up": [
        "Shyama Gero",
        "Carleigh Herbert",
        "AnnaRose Kern",
        "Regan Livingstone",
        "Hannah Lux Davis"
    ],
    "production manager": [
        "Ed Chapman",
        "Colin Hudock",
        "Christopher Kulikowski",
        "Tracey Landon",
        "Pascal Vaguelsy"
    ],
    "assistant director": [
        "Joshua Cordes",
        "Kristofer Kolpek",
        "M. Ryan Traylor",
        "Mike Tsucalas"
    ],
    "art department": [
        "Chad Bell",
        "Scott Kinsey",
        "Kino Scialabba"
    ],
    "sound crew": [
        "Bobbi Banks",
        "Elliott Barker",
        "Charlie Campagna",
        "Harry Cohen",
        "Bill R. Dean",
        "Carlton Diggs",
        "Mike Fraumeni",
        "Houston Guy",
        "Paul Hackner",
        "Greg Hedgepath",
        "Nicholas James",
        "Michael Keller",
        "Gary L. Krause",
        "Nickolas Meade",
        "Michael Miller",
        "Reza Moosavi",
        "Barry Neely",
        "Tom Ozanich",
        "David Rawlinson",
        "Herbert Rawlinson",
        "Stephen P. Robinson",
        "John Ross",
        "Joan Rowe",
        "Sean Rowe",
        "John Sisti",
        "Hermann Thumann",
        "Bob Tiwana",
        "David F. Van Slyke",
        "Daniel R. Kerr"
    ],
    "special effects": [
        "Michael Broom",
        "Alec Gillis",
        "Michael Petrucci",
        "Tom Woodruff Jr."
    ],
    "visual effects": [
        "Holli Alvarado",
        "Spencer Armajo",
        "Oliver Arnold",
        "Caitlin Atherton",
        "Jeff Atherton",
        "Nicholas Avallone",
        "Jarrod Avalos",
        "Scott Balkcom",
        "Dan Bartolucci",
        "Vincent Blin",
        "Bruce Bolden",
        "Adam Briggs",
        "Jeremy F. Butler",
        "Andrew Byrne",
        "Kevin Cahill",
        "Marco Capparelli",
        "Oscar G. Castillo",
        "Ed Chapman",
        "Trent Claus",
        "Andrew M. Collins",
        "Brian Conlon",
        "Mauro Contaldi",
        "Joshua Cordes",
        "Andy Davis",
        "Hector de la Torre",
        "Fefo Desouza",
        "Eric Ebling",
        "Tamer Eldib",
        "Josh Elmore",
        "Nicholas Elwell",
        "Marq Faulkner",
        "Patrick Flannery",
        "Philip Fraschetti",
        "Miles Friedman",
        "Joshua Galbincea",
        "Demitre Garza",
        "Don Greenberg",
        "Joshua Grow",
        "Miguel A. Guerrero",
        "Brian Hajek",
        "Brian Hanable",
        "Chris Haney",
        "Tulio Hernandez",
        "Paul Hopkins",
        "Robert Hubbard",
        "Nathan Hurlburt",
        "Atsushi Imamura",
        "J.D. Imhof",
        "Chris Ingersoll",
        "Pasha Ivanov",
        "Brian Janelli",
        "Daniel Jauregui",
        "Zack Judson",
        "Nathan Koga",
        "Eric A. Kohler",
        "Daniel Kruse",
        "Bill Kunin",
        "Billy-Vu Lam",
        "Kim LeBrane",
        "Sun Lee",
        "Max Leonard",
        "Dave Levine",
        "Randy Little",
        "Jose Lopez",
        "Alberto Lude\u00f1a",
        "Austin Martin",
        "Mark Matta",
        "Scott McLain",
        "Tony Meagher",
        "David Michaels",
        "Scott Michelson",
        "Steven Miller",
        "Young Joon Mok",
        "Chun Seong Ng",
        "Brian Nugent",
        "Chris Olivas",
        "Van Ouk",
        "Roto and Paint",
        "Eugene Paluso",
        "Bruno Parenti",
        "Jale Parsons",
        "Chris Payne",
        "John Polyson",
        "Juan Carlos Quintana",
        "Chris Radcliffe",
        "Scott Rader",
        "Pablovsky Ramos-Nieves",
        "Ben Record",
        "Gizmo Rivera",
        "Karl Rogovin",
        "Krystal Sae Eua",
        "Kino Scialabba",
        "Joel Sevilla",
        "Laura Sevilla",
        "Tim Simon",
        "Matt Siner",
        "Nick Sinnott",
        "Skyline",
        "John C. Sparks",
        "Colin Strause",
        "Greg Strause",
        "Frederick George Stuhrberg",
        "Alexander Tirasongkran",
        "Jon Tojek",
        "Shigeharu Tomotoshi",
        "Greg Tse",
        "Yuki Uehara",
        "Chris Wells",
        "Bob Wiatr",
        "C. Jerome Williams",
        "Derek Winslow",
        "Andrew Winters",
        "Yoshiya Yamada",
        "Roy Yang",
        "Michael Zavala"
    ],
    "stunt performer": [
        "Joey Anaya",
        "Brandon Beckman",
        "Brandon Cornell",
        "Darrell Davis",
        "Arturo Dickey",
        "Brian Duffy",
        "Debbie Evans",
        "Diana R. Lupo",
        "Mark Norby",
        "Dana Reed",
        "Erik Rondell",
        "Kyle Weishaar",
        "Omar Ayala"
    ],
    "camera and electrical department": [
        "Steve Albovias",
        "Brandon Alperin",
        "Federico Aragon",
        "Eli Berg",
        "Jeremy Braben",
        "Jake Capistron",
        "Nathan Carballo",
        "Matthew Castalito",
        "Joshua Cordes",
        "Cameron Dershem",
        "Noah Dille",
        "Eric Dvorsky",
        "Isaiah Fortajada",
        "Tyler Harrison",
        "Robby Hart",
        "Douglas S. Holgate",
        "Alex M. Jenkins",
        "Steve Koster",
        "Shaun Mayor",
        "Gregory Pickard",
        "Rob Pittman",
        "Johnny Segal",
        "Ian S. Takahashi",
        "John Trapman",
        "Marcus Ubungen",
        "Eric Ulbrich",
        "Eric Ulrich",
        "Pat Wallner",
        "Tim Wallner",
        "Tom Whitehead",
        "Arthur Zajac"
    ],
    "costume department": [
        "Emi Akimoto"
    ],
    "music department": [
        "Jeffrey Biggers",
        "Robert Elhai",
        "Todd Haberman",
        "Pakk Hui",
        "Eric Kalver",
        "Season Kent",
        "Gary L. Krause",
        "Bryan Lawson",
        "Michael J Mallen",
        "Dana Niu",
        "Martin Roller",
        "Paul Talkington",
        "Allan Wilson",
        "Eric Stonerook"
    ],
    "script department": [],
    "transportation department": [],
    "miscellaneous crew": [
        "Amit Awasthi",
        "Asher Blumberg",
        "Al Cerullo",
        "Angie Conners",
        "Evan Cunningham",
        "John 'Duke' Duquesnay",
        "Ian Evans",
        "Rebecca Flinn-White",
        "Tara Gerow",
        "Ruzanna Kegeyan",
        "Pablo Leda",
        "Oliver Wyatt Lewis",
        "Thomas Loftus",
        "Mark Maccora",
        "Skylar Mathey",
        "Andrew McArthur",
        "Allison Meadows",
        "Kasia Neiman",
        "Allison Paul",
        "Debbie Pearl",
        "Eva Quiroz",
        "Mahesh Ramanathan",
        "Irwin M. Rappaport",
        "John Sennet",
        "Wyatt Shaw",
        "Matthew Shreder",
        "Judith Smith",
        "Tommy Suarez",
        "Josh Sutherland",
        "John Tamburro",
        "Michael J Tamburro",
        "Spencer Wider",
        "Ryan Witherspoon",
        "Jen Woldrich",
        "David T. Woodruff",
        "Jeff Maynard",
        "Karina Wilson"
    ],
    "cast": [
        "Eric Balfour",
        "Scottie Thompson",
        "Brittany Daniel",
        "Crystal Reed",
        "Neil Hopkins",
        "David Zayas",
        "Donald Faison",
        "Robin Gammell",
        "Tanya Newbould",
        "J. Paul Boehmer",
        "Phet Mahathongdy",
        "Byron McIntyre",
        "Jackie Marin",
        "Tony Black",
        "Eliza Till",
        "James Huang",
        "Erik Rondell",
        "Johnny DeBeer",
        "Lauren Marin",
        "Matt Frels",
        "Pam Levin",
        "Andreea Florescu",
        "Leon 'Lee' Fuller",
        "Marcus Nel-Jamal Hamm",
        "Aneliese Kelly",
        "Gladys Khan",
        "Mobin Khan",
        "Elena Kolpachikova",
        "Waymond Lee",
        "Justin Reed",
        "Vanessa Ross",
        "Evan Shafran",
        "Abu Baker Siddiq"
    ],
    "name": "Skyline"
}