{
    "director": [
        "Judd Apatow"
    ],
    "writer": [
        "Amy Schumer"
    ],
    "producer": [
        "Judd Apatow",
        "Kim Caramele",
        "Josh Church",
        "Amanda Glaze",
        "David B. Householter",
        "Michael Lewen",
        "Barry Mendel",
        "Amy Schumer"
    ],
    "composer": [
        "Jon Brion"
    ],
    "cinematographer": [
        "Jody Lee Lipes"
    ],
    "editor": [
        "William Kerr",
        "Paul Zucker"
    ],
    "art direction": [
        "Deborah Jensen"
    ],
    "set decoration": [
        "Debra Schutt"
    ],
    "make up": [
        "Kevin Carter",
        "Nick Castellanos",
        "Alan D'Angerio",
        "Handri Gunawan",
        "Maya Hardinge",
        "Paula Kelly",
        "Craig Lindberg",
        "Sanja Milic",
        "Kyra Panchenko",
        "Krystle Poulin",
        "Rosemary Redlin",
        "Stanley Tines",
        "Jovan Vitagliano",
        "Stephanie Wise"
    ],
    "production manager": [
        "David B. Householter",
        "Dana Robin",
        "Lisa Rodgers"
    ],
    "assistant director": [
        "Catherine Feeny",
        "Amy Lauritsen",
        "Matt Rebenkoff",
        "Jeff Sedwick"
    ],
    "art department": [
        "Michael Acevedo Jr.",
        "Michael Acevedo",
        "Joseph A. Alfieri Jr.",
        "Michael Bruno",
        "Deborah Canfield",
        "Philip Canfield",
        "Teresa Kelly Canfield",
        "Candice Cardasis",
        "Alexios Chrysikos",
        "David Cooney",
        "Jerry DeRogatis",
        "Nicole Eckenroad",
        "Steve Fratianni",
        "Alex Gorodetsky",
        "Maria Gorodetsky",
        "Damon Hahn",
        "Chris Heaps",
        "Eric Helmin",
        "Jay Hendrickx",
        "Arlo Hoffman",
        "Gavin Holmes Jr.",
        "Richard Hoppe",
        "Edward A. Ioffreda",
        "Tina Khayat",
        "James Klotsas",
        "Eugene Paul Lynch",
        "James Mazzola",
        "Matthew Mazzola",
        "Shawn Mulligan",
        "Quang Nguyen",
        "Jennifer Alex Nickason",
        "Fanny Pereire",
        "Sharon Potts",
        "Christopher Santilli",
        "Will Scheck",
        "Nithya Shrinivasan",
        "Stavros Stamat",
        "Mike Thompson",
        "Mark Tierney",
        "Anna Weber",
        "Christopher Weiser",
        "Travis Wright",
        "Tim Zydel"
    ],
    "sound crew": [
        "George H. Anderson",
        "Justine Baker",
        "Hunter Berk",
        "Scott Cannizzaro",
        "Chris Carpenter",
        "Kristin Catuogno",
        "Mark DeSimone",
        "Angelina Faulkner",
        "Tammy Fearing",
        "Marc Fishman",
        "Christopher Flowers",
        "Sandra Fox",
        "Jack Heeren",
        "Larry Kemp",
        "Goro Koyama",
        "Jeff Levy",
        "Howard London",
        "Andy Malcolm",
        "Cindy Marty",
        "Stephen Muir",
        "Tom Nelson",
        "Allen Ormerod",
        "Derek Pacuk",
        "Fred Peck III",
        "Joe Schiff",
        "Jason Stasium",
        "Cherie Tamai",
        "Dmitry Volovik",
        "Don White"
    ],
    "special effects": [
        "Pixomondo"
    ],
    "visual effects": [
        "Michael Bogen",
        "Myong Choi",
        "Christopher Cram",
        "Scott M. Davids",
        "Nancy Duff",
        "Joshua H. Johnson",
        "Tavis Larkham",
        "Mare McIntosh",
        "Dennis Murillo",
        "Eric J. Robertson"
    ],
    "stunt performer": [
        "Luciano Acuna Jr.",
        "Bobby Beckles",
        "Ann Carton",
        "Joseph Coghlan",
        "Stacy Courtney",
        "Douglas Crosby",
        "Mark Fichera",
        "Jeffrey Lee Gibson",
        "Becca GT",
        "Warren E. Hull",
        "Samantha MacIvor",
        "Declan Mulvey",
        "Tracey Ruggiero",
        "Tom Sierchio",
        "Laurie Singer",
        "Brian Smyj",
        "Derric J. Stotts",
        "Matt Triplett",
        "Aaron Vexler"
    ],
    "camera and electrical department": [
        "John Alcantara",
        "Joe Anderson",
        "Andre Azevedo",
        "Joseph Belschner",
        "Kelly Britt",
        "Jan Burgess",
        "Daniel Casey",
        "Mariusz Cichon",
        "Alisa M. Colley",
        "Jason Cox",
        "Matt Craig",
        "Mary Cybulski",
        "Mark Cyr",
        "Andy Day",
        "Michael Day",
        "Jess Dunn",
        "Kris Enos",
        "Charlie Grubbs",
        "Emily Millay Haddad",
        "Nicholas Hahn",
        "Matthew Hale",
        "Elizabeth 'Liz' Hedges",
        "Liz Hedges",
        "Matt Hedges",
        "Brett Heicher",
        "Brian Heller",
        "Petr Hlinomaz",
        "Michael Hunold",
        "Abi Iverson",
        "Nils Johnson",
        "Billy Kerwick",
        "Kevin Kerwick",
        "Jack Kney",
        "Frank La Frazia",
        "Jennifer Leavitt",
        "Dan Levy",
        "Billy Lynch Jr.",
        "William MacGhee",
        "Loren Malo",
        "Daniel James McCabe",
        "Blaise Miller",
        "Matthew J. Monahan",
        "Adam Newport-Berra",
        "John Patrick Oates",
        "Jeff Panessa",
        "Robbin Park",
        "James Parsons",
        "Mark Petronio",
        "August Popkin",
        "Bryan Rubin",
        "Kyle Rudolph",
        "David M. Russell",
        "Jonathan Salvo",
        "Leon Sanginiti",
        "Christina See",
        "Derek Walker",
        "Aurelia Winborn",
        "John Woods",
        "Steven Search",
        "Andy Watts"
    ],
    "costume department": [
        "Gabriel Adams",
        "Jessica Bergstrom",
        "Mackenzie Caddell",
        "Bridget Chapman",
        "Randi Featherstone",
        "Robin Fitzgerald",
        "Katie Gray",
        "Nicole Greenbaum",
        "Emily Gunshor",
        "Kayti Haugh",
        "Annie Kuty",
        "Elizabeth Muxi",
        "David Turk"
    ],
    "music department": [
        "Jon Brion",
        "Celeste Chada",
        "Matt Chamberlain",
        "Greg Foeller",
        "Jonathan Leahy",
        "Alison Rosenfeld Moses",
        "Manish Raval",
        "Peter Rotter",
        "Darren Rutter",
        "Rob Simmons",
        "Steven L. Smith",
        "Tom Wolfe",
        "Gina Zimmitti"
    ],
    "script department": [
        "Thomas Johnston"
    ],
    "transportation department": [
        "David Conelli",
        "James Fanning",
        "Frank Lomuto"
    ],
    "miscellaneous crew": [
        "Adesola Adeyeye",
        "Natalie Alexander",
        "Teddy Au",
        "Jonathan Potter Barnes",
        "Andy Benavides",
        "Ryan Bernstein",
        "Dustin Bewley",
        "Cameron Boone",
        "Christopher Britton",
        "Chris Burns",
        "Michelle D. Camero",
        "Marlo Carroll",
        "Al Cerullo",
        "Brock T. Charde",
        "Brendan Clougherty",
        "Angie Lee Cobbs",
        "Jason Cox",
        "Samantha Dyer",
        "Bradford Eaves",
        "Mark Robert Ellis",
        "Nicole Evranian",
        "Chase Fein",
        "Kiera Fellegara",
        "Rich Fellegara",
        "Danielle Flora",
        "Jamie Horwitz",
        "Alexis Hughes",
        "Rachel Jaros",
        "Kevin Kane",
        "Kyle Knauf",
        "Ron Kochie",
        "Kim Krafsky",
        "Julie Kuehndorf",
        "Josh LaJoie",
        "Christine Magdalene",
        "David Midgen",
        "John J. Moers",
        "Lisa Monahan",
        "Kimberly Ndombe",
        "Jes Norris",
        "Nick Notte",
        "Kristy Pace",
        "Harley Pasternak",
        "Kerry Roberts",
        "Matthew Roper",
        "Barbie Ross",
        "Cassandra Santiago",
        "Jessi Sheldon",
        "Luke Tomalin Sherman",
        "Spencer Soloman",
        "Stephanie L. Sparks",
        "Alexis M. Steinbach",
        "Logan Thoreau",
        "Danny Vallentine",
        "Erena Willis",
        "Mitchell Wu",
        "Sara DeRosa"
    ],
    "cast": [
        "Colin Quinn",
        "Devin Fabry",
        "Carla Oudin",
        "Amy Schumer",
        "Josh Segarra",
        "Ryan Farrell",
        "Robert E. Torres",
        "Jim Florentine",
        "Robert Kelly",
        "Dan Soder",
        "John Cena",
        "Dave Attell",
        "Vanessa Bayer",
        "Tilda Swinton",
        "Randall Park",
        "Jon Glaser",
        "Ezra Miller",
        "Brie Larson",
        "Evan Brinkman",
        "Mike Birbiglia",
        "Norman Lloyd",
        "Bill Hader",
        "LeBron James",
        "Daniel Radcliffe",
        "Marisa Tomei",
        "Keith Robinson",
        "Marina Franklin",
        "Dave Hanson",
        "Pete Davidson",
        "Kim Caramele",
        "Method Man",
        "Max Alexander",
        "Criscia Richardson",
        "Claudia O'Doherty",
        "Kyle Dunnigan",
        "Kevin Kane",
        "Tim Meadows",
        "Nikki Glaser",
        "Bridget Everett",
        "Alva Chinn",
        "Arnold Y. Kim",
        "Rob Buntzen",
        "Karen Chamberlain",
        "Ajay Mehta",
        "Tony Romo",
        "Amar'e Stoudemire",
        "Rachel Feinstein",
        "Victoria Dicce",
        "Lisa K. Price",
        "Matthew Broderick",
        "Marv Albert",
        "Chris Evert",
        "Kevin Thompson",
        "Leslie Jones",
        "Estee Adoram",
        "Leah O'Donnell",
        "Selena Watkins",
        "Alicia Mazepa",
        "Nicole Serapiglia",
        "Amanda Robinson",
        "Whitney Wiggins",
        "Alexa Kobylarz",
        "Ashley Nuel",
        "Michele Roe",
        "Teal DePaola",
        "Latoya Brooks",
        "Kerrie Greene",
        "Jess Attardo",
        "Alyssa Quezada",
        "Javoirs Carlisle",
        "Aidan Charlery",
        "Warren E. Hull",
        "Eric Locklin",
        "Luciano Acuna Jr.",
        "Derric J. Stotts",
        "Sterling Jones",
        "Roger Brenner",
        "Jos\u00e9 B\u00e1ez",
        "Tony Cheng",
        "Jessica Cherniak",
        "Marmee Regine Cosico",
        "Patrick J. Curley",
        "Jedidiah Dore",
        "Christine Duke",
        "Tim Duquette",
        "Scott Eliasoph",
        "Damon C. Fields",
        "Patrice Francois",
        "Henry Gagliardi",
        "Booker Garrett",
        "Robert Z. Grant",
        "Matthew Herington",
        "Liam Higgins",
        "Liz Imperio",
        "Kimberly L. Jackson",
        "Emma Jonnz",
        "Diane Kimbrell",
        "Rock Kohli",
        "Christina Lancaster",
        "Parker Madison",
        "John Mainieri",
        "Joe Mancini",
        "Sebastian Marocola",
        "Danny L. Martin",
        "Doris McCarthy",
        "Khalil Muhammad",
        "Chase Murray",
        "Romesh Radhakrishnan",
        "Eddie K. Robinson",
        "Michael A. Russo",
        "Robert Sage",
        "Edward Sass",
        "Chris Skeries",
        "Holly Stanford",
        "Krista Tunnell"
    ],
    "name": "Trainwreck"
}